ifsFractals/__init__.py
ifsFractals-1.0.4.dist-info/LICENSE
ifsFractals-1.0.4.dist-info/METADATA
ifsFractals-1.0.4.dist-info/WHEEL
ifsFractals-1.0.4.dist-info/top_level.txt
ifsFractals-1.0.4.dist-info/RECORD
