Metadata-Version: 2.1
Name: ifsFractals
Version: 1.0.4
Summary: For Fast Generation of IFS Fractals
Home-page: https://github.com/PeterEFrancis/ifsFractals-py
Author: Peter Francis
Author-email: peter.e.francis@stonybrook.edu
Keywords: Fractal Generator
Requires-Python: >=3.0.0
License-File: LICENSE
Requires-Dist: imageio
Requires-Dist: matplotlib
Requires-Dist: numpy
Requires-Dist: Pillow
Requires-Dist: IPython
